{
    "name":"Widget manager",
    "version":"1.0.0",
    "author":"Francesco Pepe",
    "location":"https://github.com/contentbox-modules/widget-manager/archive/master.zip",
    "directory":"",
    "createPackageDirectory":true,
    "packageDirectory":"",
    "homepage":"https://github.com/contentbox-modules/widget-manager",
    "documentation":"",
    "repository":{
        "type":"",
        "URL":""
    },
    "bugs":"",
    "slug":"widget-manager",
    "shortDescription":"A module to manage widget and contentstore with drag&drop",
    "description":"",
    "instructions":"",
    "changelog":"",
    "type":"",
    "keywords":"widget,drag&drop,widget manager",
    "private":false,
    "engines":[
        {
            "type":"",
            "version":""
        }
    ],
    "defaultEngine":"",
    "defaultPort":0,
    "projectURL":"",
    "license":[
        {
            "type":"",
            "URL":""
        }
    ],
    "contributors":[
        
    ],
    "dependencies":{
        
    },
    "devDependencies":{
        
    },
    "installPaths":{
        
    },
    "scripts":{
        
    },
    "ignore":[
        "**/.*",
        "test",
        "tests"
    ],
    "testbox":{
        "runner":[
            {
                "default":""
            }
        ],
        "labels":[
            
        ],
        "reporter":"",
        "reporterResults":"",
        "bundles":[
            ""
        ],
        "directory":{
            "mapping":"",
            "recurse":true
        },
        "watchers":[
            
        ],
        "notify":{
            "emails":[
                
            ],
            "growl":"",
            "URL":""
        }
    }
}